avrdude_windows/__init__.py
avrdude_windows/avrdude_binaries/x32/avrdude.conf
avrdude_windows/avrdude_binaries/x32/avrdude.exe
avrdude_windows/avrdude_binaries/x64/avrdude.conf
avrdude_windows/avrdude_binaries/x64/avrdude.exe
avrdude_windows-7.1.0.dist-info/LICENSE
avrdude_windows-7.1.0.dist-info/METADATA
avrdude_windows-7.1.0.dist-info/WHEEL
avrdude_windows-7.1.0.dist-info/top_level.txt
avrdude_windows-7.1.0.dist-info/RECORD
