Metadata-Version: 2.1
Name: avrdude-windows
Version: 7.1.0
Summary: A pypi package containing avrdude binaries for Windows
Project-URL: Homepage, https://github.com/jeremyherbert/avrdude_windows_pypi
Classifier: Operating System :: Microsoft :: Windows
Classifier: Topic :: Software Development :: Embedded Systems
Classifier: License :: OSI Approved :: MIT License
License-File: LICENSE
